setup.py
RGPerson/RGPerson.py
RGPerson/__init__.py
RGPerson/districtcode.py
RGPerson.egg-info/PKG-INFO
RGPerson.egg-info/SOURCES.txt
RGPerson.egg-info/dependency_links.txt
RGPerson.egg-info/top_level.txt