Metadata-Version: 1.0
Name: RGPerson
Version: 0.1
Summary: RGPerson
Home-page: https://github.com/gh0stkey/RGPerson
Author: Vulkey_Chen
Author-email: admin@gh0st.cn
License: MIT Licence
Keywords: pip,rgperson,featureextraction
Platform: any
